{
  "POIs": [
    {
      "fit": [
        0.6753321290016174,
        0.699999988079071,
        0.7232283353805542
      ],
      "name": "Ac"
    },
    {
      "fit": [
        0.9175763130187988,
        1.0,
        1.1477103233337402
      ],
      "name": "r_neg"
    }
  ],
  "method": "default",
  "params": [
    {
      "Ac": [
        0.6955594420433044,
        0.699999988079071,
        0.6909846663475037
      ],
      "fit": [
        -0.21900150179862976,
        2.76489942052649e-12,
        0.21653717756271362
      ],
      "groups": [],
      "impact_Ac": 0.009015321731567383,
      "impact_r_neg": 0.05472373962402344,
      "name": "Others_norm",
      "prefit": [
        -0.9999999999999999,
        0.0,
        0.9999999999999999
      ],
      "r_neg": [
        0.9874274134635925,
        1.0,
        1.0547237396240234
      ],
      "type": "Gaussian"
    },
    {
      "Ac": [
        0.6950883865356445,
        0.699999988079071,
        0.6948599219322205
      ],
      "fit": [
        -0.18571871519088745,
        1.1790834975045072e-10,
        0.17913232743740082
      ],
      "groups": [],
      "impact_Ac": 0.005140066146850586,
      "impact_r_neg": 0.0372699499130249,
      "name": "ST_norm",
      "prefit": [
        -0.9999999999999999,
        0.0,
        0.9999999999999999
      ],
      "r_neg": [
        0.9951723217964172,
        1.0,
        1.037269949913025
      ],
      "type": "Gaussian"
    },
    {
      "Ac": [
        0.6998768448829651,
        0.699999988079071,
        0.6990886926651001
      ],
      "fit": [
        -0.9922904372215271,
        3.2484255285680774e-09,
        0.9895980358123779
      ],
      "groups": [],
      "impact_Ac": 0.0009112954139709473,
      "impact_r_neg": 0.042301177978515625,
      "name": "TTbar_norm",
      "prefit": [
        -0.9999999999999999,
        0.0,
        0.9999999999999999
      ],
      "r_neg": [
        1.0423011779785156,
        1.0,
        0.9590985774993896
      ],
      "type": "Gaussian"
    },
    {
      "Ac": [
        0.6997647285461426,
        0.699999988079071,
        0.6904210448265076
      ],
      "fit": [
        -0.4502430558204651,
        1.0397940286566154e-09,
        0.4389474391937256
      ],
      "groups": [],
      "impact_Ac": 0.009578943252563477,
      "impact_r_neg": 0.08370602130889893,
      "name": "btagCferr1",
      "prefit": [
        -1.0,
        0.0,
        1.0
      ],
      "r_neg": [
        1.083706021308899,
        1.0,
        0.9852330088615417
      ],
      "type": "Gaussian"
    },
    {
      "Ac": [
        0.6998969316482544,
        0.699999988079071,
        0.6892049312591553
      ],
      "fit": [
        -0.4557753801345825,
        1.3376738827730605e-08,
        0.45053672790527344
      ],
      "groups": [],
      "impact_Ac": 0.010795056819915771,
      "impact_r_neg": 0.056182861328125,
      "name": "btagCferr2",
      "prefit": [
        -1.0,
        0.0,
        1.0
      ],
      "r_neg": [
        1.056182861328125,
        1.0,
        1.0066213607788086
      ],
      "type": "Gaussian"
    },
    {
      "Ac": [
        0.6905685067176819,
        0.699999988079071,
        0.6905369758605957
      ],
      "fit": [
        -0.3740164041519165,
        0.0,
        0.3423982560634613
      ],
      "groups": [],
      "impact_Ac": 0.009463012218475342,
      "impact_r_neg": 0.03264570236206055,
      "name": "btagHf",
      "prefit": [
        -1.0,
        0.0,
        1.0
      ],
      "r_neg": [
        1.0326457023620605,
        1.0,
        1.0167583227157593
      ],
      "type": "Gaussian"
    },
    {
      "Ac": [
        0.6875220537185669,
        0.699999988079071,
        0.6867304444313049
      ],
      "fit": [
        -0.4524557888507843,
        0.0,
        0.4589085578918457
      ],
      "groups": [],
      "impact_Ac": 0.013269543647766113,
      "impact_r_neg": 0.03396773338317871,
      "name": "btagHfstats1",
      "prefit": [
        -1.0,
        0.0,
        1.0
      ],
      "r_neg": [
        1.0333120822906494,
        1.0,
        1.0339677333831787
      ],
      "type": "Gaussian"
    },
    {
      "Ac": [
        0.6866879463195801,
        0.699999988079071,
        0.6873973608016968
      ],
      "fit": [
        -0.459170937538147,
        -1.0927641014291112e-09,
        0.45344170928001404
      ],
      "groups": [],
      "impact_Ac": 0.013312041759490967,
      "impact_r_neg": 0.03500103950500488,
      "name": "btagHfstats2",
      "prefit": [
        -1.0,
        0.0,
        1.0
      ],
      "r_neg": [
        1.0319064855575562,
        1.0,
        1.0350010395050049
      ],
      "type": "Gaussian"
    },
    {
      "Ac": [
        0.6862814426422119,
        0.699999988079071,
        0.6884520053863525
      ],
      "fit": [
        -0.46208900213241577,
        -1.6459789087264198e-09,
        0.44154155254364014
      ],
      "groups": [],
      "impact_Ac": 0.01371854543685913,
      "impact_r_neg": 0.038646817207336426,
      "name": "btagLf",
      "prefit": [
        -1.0,
        0.0,
        1.0
      ],
      "r_neg": [
        1.0386468172073364,
        1.0,
        1.0331611633300781
      ],
      "type": "Gaussian"
    },
    {
      "Ac": [
        0.6877331137657166,
        0.6999999284744263,
        0.6867390871047974
      ],
      "fit": [
        -0.46063441038131714,
        -1.1946786671046539e-08,
        0.4474477469921112
      ],
      "groups": [],
      "impact_Ac": 0.013260841369628906,
      "impact_r_neg": 0.045928239822387695,
      "name": "btagLfstats1",
      "prefit": [
        -1.0,
        0.0,
        1.0
      ],
      "r_neg": [
        1.02129065990448,
        1.0,
        1.0459282398223877
      ],
      "type": "Gaussian"
    },
    {
      "Ac": [
        0.6878824234008789,
        0.699999988079071,
        0.6867409944534302
      ],
      "fit": [
        -0.4558921158313751,
        -1.056588594394725e-09,
        0.4432311952114105
      ],
      "groups": [],
      "impact_Ac": 0.01325899362564087,
      "impact_r_neg": 0.04160881042480469,
      "name": "btagLfstats2",
      "prefit": [
        -1.0,
        0.0,
        1.0
      ],
      "r_neg": [
        1.0246577262878418,
        1.0,
        1.0416088104248047
      ],
      "type": "Gaussian"
    },
    {
      "Ac": [
        0.6869157552719116,
        0.699999988079071,
        0.6881125569343567
      ],
      "fit": [
        -0.4611033797264099,
        5.751932263819981e-10,
        0.43857958912849426
      ],
      "groups": [],
      "impact_Ac": 0.013084232807159424,
      "impact_r_neg": 0.04163229465484619,
      "name": "fsr",
      "prefit": [
        -1.0,
        0.0,
        1.0
      ],
      "r_neg": [
        1.0416322946548462,
        1.0,
        1.0259588956832886
      ],
      "type": "Gaussian"
    },
    {
      "Ac": [
        0.6873248815536499,
        0.699999988079071,
        0.6868447065353394
      ],
      "fit": [
        -0.4551001191139221,
        3.483445709662192e-08,
        0.4565492868423462
      ],
      "groups": [],
      "impact_Ac": 0.01315528154373169,
      "impact_r_neg": 0.03663170337677002,
      "name": "isr",
      "prefit": [
        -1.0,
        0.0,
        1.0
      ],
      "r_neg": [
        1.03663170337677,
        1.0,
        1.0308480262756348
      ],
      "type": "Gaussian"
    },
    {
      "Ac": [
        0.703949511051178,
        0.699999988079071,
        0.6990600824356079
      ],
      "fit": [
        -0.7897697687149048,
        1.201754251667353e-09,
        0.7684797644615173
      ],
      "groups": [],
      "impact_Ac": 0.003949522972106934,
      "impact_r_neg": 0.039551734924316406,
      "name": "jec",
      "prefit": [
        -1.0,
        0.0,
        1.0
      ],
      "r_neg": [
        1.0395517349243164,
        1.0,
        0.970467209815979
      ],
      "type": "Gaussian"
    },
    {
      "Ac": [
        0.7030301690101624,
        0.699999988079071,
        0.7012729644775391
      ],
      "fit": [
        -0.9476497173309326,
        1.9832198105973475e-09,
        0.927459180355072
      ],
      "groups": [],
      "impact_Ac": 0.0030301809310913086,
      "impact_r_neg": 0.0016883611679077148,
      "name": "jer",
      "prefit": [
        -1.0,
        0.0,
        1.0
      ],
      "r_neg": [
        1.0016883611679077,
        1.0,
        0.9992466568946838
      ],
      "type": "Gaussian"
    },
    {
      "Ac": [
        0.7000993490219116,
        0.699999988079071,
        0.6989586353302002
      ],
      "fit": [
        -0.9898618459701538,
        1.793255322013465e-09,
        0.9900975227355957
      ],
      "groups": [],
      "impact_Ac": 0.0010413527488708496,
      "impact_r_neg": 0.009088277816772461,
      "name": "lumi",
      "prefit": [
        -0.9999999999999999,
        0.0,
        0.9999999999999999
      ],
      "r_neg": [
        1.0090882778167725,
        1.0,
        0.9928944706916809
      ],
      "type": "Gaussian"
    },
    {
      "Ac": [
        0.7000296115875244,
        0.699999988079071,
        0.6985418200492859
      ],
      "fit": [
        -0.9847319722175598,
        0.0,
        0.9873020052909851
      ],
      "groups": [],
      "impact_Ac": 0.0014581680297851562,
      "impact_r_neg": 0.011879563331604004,
      "name": "lumi_corr_161718",
      "prefit": [
        -0.9999999999999999,
        0.0,
        0.9999999999999999
      ],
      "r_neg": [
        1.011879563331604,
        1.0,
        0.9909335374832153
      ],
      "type": "Gaussian"
    },
    {
      "Ac": [
        0.7000292539596558,
        0.699999988079071,
        0.6999286413192749
      ],
      "fit": [
        -0.9941874742507935,
        1.5759145099991656e-09,
        0.994044840335846
      ],
      "groups": [],
      "impact_Ac": 7.134675979614258e-05,
      "impact_r_neg": 0.00020444393157958984,
      "name": "lumi_corr_1718",
      "prefit": [
        -0.9999999999999999,
        0.0,
        0.9999999999999999
      ],
      "r_neg": [
        1.0002044439315796,
        1.0,
        0.999936580657959
      ],
      "type": "Gaussian"
    },
    {
      "Ac": [
        0.7001176476478577,
        0.6999999284744263,
        0.6989556550979614
      ],
      "fit": [
        -0.9896352887153625,
        1.5206389036848122e-08,
        0.9877345561981201
      ],
      "groups": [],
      "impact_Ac": 0.0010442733764648438,
      "impact_r_neg": 0.008553266525268555,
      "name": "lumi_uncorr_18",
      "prefit": [
        -0.9999999999999999,
        0.0,
        0.9999999999999999
      ],
      "r_neg": [
        1.0085532665252686,
        1.0,
        0.993647575378418
      ],
      "type": "Gaussian"
    },
    {
      "Ac": [
        0.6872486472129822,
        0.699999988079071,
        0.6868588924407959
      ],
      "fit": [
        -0.4542422294616699,
        5.037230188520425e-09,
        0.45835480093955994
      ],
      "groups": [],
      "impact_Ac": 0.013141095638275146,
      "impact_r_neg": 0.034012794494628906,
      "name": "muonID",
      "prefit": [
        -1.0,
        0.0,
        1.0
      ],
      "r_neg": [
        1.0336813926696777,
        1.0,
        1.034012794494629
      ],
      "type": "Gaussian"
    },
    {
      "Ac": [
        0.6870236992835999,
        0.699999988079071,
        0.687086284160614
      ],
      "fit": [
        -0.4566110372543335,
        1.0117799931208538e-09,
        0.4560440480709076
      ],
      "groups": [],
      "impact_Ac": 0.012976288795471191,
      "impact_r_neg": 0.03386104106903076,
      "name": "muonIso",
      "prefit": [
        -1.0,
        0.0,
        1.0
      ],
      "r_neg": [
        1.0338610410690308,
        1.0,
        1.0336636304855347
      ],
      "type": "Gaussian"
    },
    {
      "Ac": [
        0.6873765587806702,
        0.699999988079071,
        0.6869205832481384
      ],
      "fit": [
        -0.4539766311645508,
        1.997835497036249e-08,
        0.45799386501312256
      ],
      "groups": [],
      "impact_Ac": 0.013079404830932617,
      "impact_r_neg": 0.03406965732574463,
      "name": "muonTrigger",
      "prefit": [
        -1.0,
        0.0,
        1.0
      ],
      "r_neg": [
        1.0340696573257446,
        1.0,
        1.0331696271896362
      ],
      "type": "Gaussian"
    },
    {
      "Ac": [
        0.7199318408966064,
        0.699999988079071,
        0.6808445453643799
      ],
      "fit": [
        -0.6726706027984619,
        0.0,
        0.23179899156093597
      ],
      "groups": [],
      "impact_Ac": 0.0199318528175354,
      "impact_r_neg": 0.007139086723327637,
      "name": "murmuf",
      "prefit": [
        -1.0,
        0.0,
        1.0
      ],
      "r_neg": [
        0.9928609132766724,
        1.0,
        1.0064811706542969
      ],
      "type": "Gaussian"
    },
    {
      "Ac": [
        0.6920648217201233,
        0.699999988079071,
        0.6969912052154541
      ],
      "fit": [
        -0.09701515734195709,
        0.0,
        0.10028918832540512
      ],
      "groups": [],
      "impact_Ac": 0.007935166358947754,
      "impact_r_neg": 0.005011916160583496,
      "name": "pdf",
      "prefit": [
        -1.0,
        0.0,
        1.0
      ],
      "r_neg": [
        0.9960314035415649,
        1.0,
        1.0050119161605835
      ],
      "type": "Gaussian"
    },
    {
      "Ac": [
        0.687096893787384,
        0.699999988079071,
        0.6869520545005798
      ],
      "fit": [
        -0.4573081433773041,
        -1.3133050202895902e-09,
        0.45545804500579834
      ],
      "groups": [],
      "impact_Ac": 0.013047933578491211,
      "impact_r_neg": 0.034024953842163086,
      "name": "prefiringWeight",
      "prefit": [
        -1.0,
        0.0,
        1.0
      ],
      "r_neg": [
        1.033424973487854,
        1.0,
        1.034024953842163
      ],
      "type": "Gaussian"
    },
    {
      "Ac": [
        0.6867259740829468,
        0.699999988079071,
        0.6875971555709839
      ],
      "fit": [
        -0.45811596512794495,
        4.441853107550742e-09,
        0.44396114349365234
      ],
      "groups": [],
      "impact_Ac": 0.013274013996124268,
      "impact_r_neg": 0.03503608703613281,
      "name": "pu",
      "prefit": [
        -1.0,
        0.0,
        1.0
      ],
      "r_neg": [
        1.03175687789917,
        1.0,
        1.0350360870361328
      ],
      "type": "Gaussian"
    },
    {
      "Ac": [
        0.6865772604942322,
        0.699999988079071,
        0.6877769231796265
      ],
      "fit": [
        -0.46554774045944214,
        3.6415022108826633e-09,
        0.4443207383155823
      ],
      "groups": [],
      "impact_Ac": 0.013422727584838867,
      "impact_r_neg": 0.03504312038421631,
      "name": "tmistag",
      "prefit": [
        -1.0,
        0.0,
        1.0
      ],
      "r_neg": [
        1.0350431203842163,
        1.0,
        1.0319631099700928
      ],
      "type": "Gaussian"
    },
    {
      "Ac": [
        0.6880559325218201,
        0.699999988079071,
        0.6862246990203857
      ],
      "fit": [
        -0.4588853716850281,
        5.747679665546457e-09,
        0.4507148861885071
      ],
      "groups": [],
      "impact_Ac": 0.013775289058685303,
      "impact_r_neg": 0.034454941749572754,
      "name": "ttagCorr",
      "prefit": [
        -1.0,
        0.0,
        1.0
      ],
      "r_neg": [
        1.0344549417495728,
        1.0,
        1.032004475593567
      ],
      "type": "Gaussian"
    },
    {
      "Ac": [
        0.6882949471473694,
        0.6999999284744263,
        0.6860279440879822
      ],
      "fit": [
        -0.4568990468978882,
        2.8063569246228326e-08,
        0.4529888331890106
      ],
      "groups": [],
      "impact_Ac": 0.013971984386444092,
      "impact_r_neg": 0.035291194915771484,
      "name": "ttagUncorr",
      "prefit": [
        -1.0,
        0.0,
        1.0
      ],
      "r_neg": [
        1.0352911949157715,
        1.0,
        1.0314984321594238
      ],
      "type": "Gaussian"
    }
  ]
}